stripe_repr/__init__.py
stripe_repr/repr.py
stripe_repr-1.0.2.dist-info/WHEEL
stripe_repr-1.0.2.dist-info/METADATA
stripe_repr-1.0.2.dist-info/RECORD
